llm_functional_agents/__init__.py
llm_functional_agents/config.py
llm_functional_agents/core/__init__.py
llm_functional_agents/core/agent_executor.py
llm_functional_agents/core/llm_backends.py
llm_functional_agents/core/llm_function.py
llm_functional_agents/core/sandbox_executor.py
llm_functional_agents/exceptions.py
llm_functional_agents/utils/__init__.py
llm_functional_agents/utils/context_manager.py
llm_functional_agents/utils/prompts.py
llm_functional_agents-0.1.1.dist-info/LICENSE
llm_functional_agents-0.1.1.dist-info/METADATA
llm_functional_agents-0.1.1.dist-info/WHEEL
llm_functional_agents-0.1.1.dist-info/RECORD
