Metadata-Version: 2.3
Name: llm-functional-agents
Version: 0.1.1
Summary: A lightweight Python library for creating reliable, contract-driven LLM functions whose core logic is implemented by an LLM.
License: MIT
Keywords: llm,functions,ai,agent,pydantic,openai,openrouter
Author: Jacob Ewen
Author-email: jacobt.ewen@gmail.com
Requires-Python: >=3.9,<3.13
Classifier: Development Status :: 3 - Alpha
Classifier: Intended Audience :: Developers
Classifier: License :: OSI Approved :: MIT License
Classifier: Operating System :: OS Independent
Classifier: Programming Language :: Python :: 3
Classifier: Programming Language :: Python :: 3.9
Classifier: Programming Language :: Python :: 3.10
Classifier: Programming Language :: Python :: 3.11
Classifier: Programming Language :: Python :: 3.12
Classifier: Topic :: Scientific/Engineering :: Artificial Intelligence
Classifier: Topic :: Software Development :: Libraries :: Python Modules
Requires-Dist: openai (>=1.0.0,<2.0.0)
Requires-Dist: pydantic (>=2.0,<3.0)
Requires-Dist: python-dotenv (>=1.0.0,<2.0.0)
Project-URL: Homepage, https://github.com/jtewen/llm-functional-agents
Project-URL: Repository, https://github.com/jtewen/llm-functional-agents
